mongodb_connect/__init__.py
mongodb_connect/mongo_crud.py
mongocommands-0.0.5.dist-info/LICENSE
mongocommands-0.0.5.dist-info/METADATA
mongocommands-0.0.5.dist-info/WHEEL
mongocommands-0.0.5.dist-info/top_level.txt
mongocommands-0.0.5.dist-info/RECORD
